nsingleton-0.1.0.dist-info/METADATA
nsingleton-0.1.0.dist-info/WHEEL
nsingleton-0.1.0.dist-info/licenses/LICENSE
nsingleton/__init__.py
nsingleton/nsingleton.py
nsingleton-0.1.0.dist-info/RECORD
