Metadata-Version: 2.1
Name: nsingleton
Version: 0.1.0
Summary: New Singleton decorator. Just another singleton pattern implementation. Thread-safe, with type casting.
Keywords: python singleton pattern decorator
Author-Email: Nikolay Shishov <nikolay.shishov@gmail.com>
License: MIT License
Classifier: Programming Language :: Python :: 3
Classifier: License :: OSI Approved :: MIT License
Classifier: Operating System :: OS Independent
Project-URL: Repository, https://github.com/nickosh/nsingleton
Requires-Python: >=3.8
